odoo8_addon_l10n_nl_partner_name-8.0.1.0.0-py2.7-nspkg.pth
odoo_addons/l10n_nl_partner_name/__openerp__.py
odoo_addons/l10n_nl_partner_name/__init__.py
odoo_addons/l10n_nl_partner_name/README.rst
odoo_addons/l10n_nl_partner_name/view/res_partner.xml
odoo_addons/l10n_nl_partner_name/i18n/l10n_nl_partner_name.pot
odoo_addons/l10n_nl_partner_name/i18n/nl.po
odoo_addons/l10n_nl_partner_name/model/res_partner.py
odoo_addons/l10n_nl_partner_name/model/__init__.py
odoo_addons/l10n_nl_partner_name/scripts/guess_names.py
odoo_addons/l10n_nl_partner_name/tests/test_l10n_nl_partner_name.py
odoo_addons/l10n_nl_partner_name/tests/__init__.py
odoo_addons/l10n_nl_partner_name/static/src/img/icon.png
odoo8_addon_l10n_nl_partner_name-8.0.1.0.0.dist-info/top_level.txt
odoo8_addon_l10n_nl_partner_name-8.0.1.0.0.dist-info/WHEEL
odoo8_addon_l10n_nl_partner_name-8.0.1.0.0.dist-info/RECORD
odoo8_addon_l10n_nl_partner_name-8.0.1.0.0.dist-info/metadata.json
odoo8_addon_l10n_nl_partner_name-8.0.1.0.0.dist-info/DESCRIPTION.rst
odoo8_addon_l10n_nl_partner_name-8.0.1.0.0.dist-info/METADATA
odoo8_addon_l10n_nl_partner_name-8.0.1.0.0.dist-info/namespace_packages.txt
