Metadata-Version: 2.0
Name: odoo8-addon-l10n-nl-partner-name
Version: 8.0.1.0.0
Summary: Dutch partner names
Home-page: UNKNOWN
Author: UNKNOWN
Author-email: UNKNOWN
License: UNKNOWN
Platform: UNKNOWN
Requires-Dist: mako
Requires-Dist: odoo (<9.0a,>=8.0a)
Requires-Dist: odoo8-addon-partner-firstname
Classifier: Programming Language :: Python :: 2.7
Classifier: Framework :: Odoo
